Workbook

Sheet P&L 2026 all
B1: Доход от реализации | C1: Январь | D1: Февраль | E1: Март | F1: Апрель | G1: Май | H1: Июнь | I1: Июль | J1: Август | K1: Сентябрь | L1: Октябрь | M1: Ноябрь | N1: Декабрь | O1: ИТОГО
B3: Доход от реализации | C3: ='P&L 2026 TCO'!C3+'P&L 2026 concrete'!C3+'P&L KPO'!C3 | D3: ='P&L 2026 TCO'!D3+'P&L 2026 concrete'!D3+'P&L KPO'!D3 | E3: ='P&L 2026 TCO'!E3+'P&L 2026 concrete'!E3+'P&L KPO'!E3 | F3: ='P&L 2026 TCO'!F3+'P&L 2026 concrete'!F3 | G3: ='P&L 2026 TCO'!G3+'P&L 2026 concrete'!G3 | H3: ='P&L 2026 TCO'!H3+'P&L 2026 concrete'!H3 | I3: ='P&L 2026 TCO'!I3+'P&L 2026 concrete'!I3 | J3: ='P&L 2026 TCO'!J3+'P&L 2026 concrete'!J3 | K3: ='P&L 2026 TCO'!K3+'P&L 2026 concrete'!K3 | L3: ='P&L 2026 TCO'!L3+'P&L 2026 concrete'!L3 | M3: ='P&L 2026 TCO'!M3+'P&L 2026 concrete'!M3 | N3: ='P&L 2026 TCO'!N3+'P&L 2026 concrete'!N3 | O3: =SUM(C3:N3)
B4: Доход от сдачи в аренду | C4: ='P&L 2026 concrete'!C4 | D4: ='P&L 2026 concrete'!D4 | E4: ='P&L 2026 concrete'!E4 | F4: ='P&L 2026 concrete'!F4 | G4: ='P&L 2026 concrete'!G4 | H4: ='P&L 2026 concrete'!H4 | I4: ='P&L 2026 concrete'!I4 | J4: ='P&L 2026 concrete'!J4 | ... N4: ='P&L 2026 concrete'!N4 | O4: =SUM(C4:N4)
B5: Прочий доход | C5: ='P&L 2026 concrete'!C5 | D5: ='P&L 2026 concrete'!D5 | E5: ='P&L 2026 concrete'!E5 | F5: ='P&L 2026 concrete'!F5 | G5: ='P&L 2026 concrete'!G5 | H5: ='P&L 2026 concrete'!H5 | I5: ='P&L 2026 concrete'!I5 | J5: ='P&L 2026 concrete'!J5 | ... N5: ='P&L 2026 concrete'!N5 | O5: =SUM(C5:N5)
B6: Прочие доходы (субсидии Даму) | C6: ='P&L 2026 concrete'!C6 | D6: ='P&L 2026 concrete'!D6 | E6: ='P&L 2026 concrete'!E6 | F6: ='P&L 2026 concrete'!F6 | G6: ='P&L 2026 concrete'!G6 | H6: ='P&L 2026 concrete'!H6 | I6: ='P&L 2026 concrete'!I6 | J6: ='P&L 2026 concrete'!J6 | ... N6: ='P&L 2026 concrete'!N6 | O6: =SUM(C6:N6)
B7: ИТОГО | C7: =SUM(C3:C6) | D7: =SUM(D3:D6) | E7: =SUM(E3:E6) | F7: =SUM(F3:F6) | G7: =SUM(G3:G6) | H7: =SUM(H3:H6) | I7: =SUM(I3:I6) | J7: =SUM(J3:J6) | ... N7: =SUM(N3:N6) | O7: =SUM(O2:O6)
B8: Расходы ТШО и Бетон
B9: GPS | C9: ='P&L 2026 TCO'!C7+'P&L KPO'!C7+'P&L 2026 concrete'!C9 | D9: ='P&L 2026 TCO'!D7+'P&L KPO'!D7+'P&L 2026 concrete'!D9 | E9: ='P&L 2026 TCO'!E7+'P&L KPO'!E7+'P&L 2026 concrete'!E9 | F9: ='P&L 2026 TCO'!F7+'P&L KPO'!F7+'P&L 2026 concrete'!F9 | G9: ='P&L 2026 TCO'!G7+'P&L KPO'!G7+'P&L 2026 concrete'!G9 | H9: ='P&L 2026 TCO'!H7+'P&L KPO'!H7+'P&L 2026 concrete'!H9 | I9: ='P&L 2026 TCO'!I7+'P&L KPO'!I7+'P&L 2026 concrete'!I9 | J9: ='P&L 2026 TCO'!J7+'P&L KPO'!J7+'P&L 2026 concrete'!J9 | ... N9: ='P&L 2026 TCO'!N7+'P&L KPO'!N7+'P&L 2026 concrete'!N9 | O9: =SUM(C9:N9)
B10: Амортизация | C10: ='P&L 2026 TCO'!C8+'P&L KPO'!C8+'P&L 2026 concrete'!C28 | D10: ='P&L 2026 TCO'!D8+'P&L KPO'!D8+'P&L 2026 concrete'!D28 | E10: ='P&L 2026 TCO'!E8+'P&L KPO'!E8+'P&L 2026 concrete'!E28 | F10: ='P&L 2026 TCO'!F8+'P&L KPO'!F8+'P&L 2026 concrete'!F28 | G10: ='P&L 2026 TCO'!G8+'P&L KPO'!G8+'P&L 2026 concrete'!G28 | H10: ='P&L 2026 TCO'!H8+'P&L KPO'!H8+'P&L 2026 concrete'!H28 | I10: ='P&L 2026 TCO'!I8+'P&L KPO'!I8+'P&L 2026 concrete'!I28 | J10: ='P&L 2026 TCO'!J8+'P&L KPO'!J8+'P&L 2026 concrete'!J28 | ... N10: ='P&L 2026 TCO'!N8+'P&L KPO'!N8+'P&L 2026 concrete'!N28 | O10: =SUM(C10:N10)
B11: Аренда офиса | C11: ='P&L 2026 TCO'!C9+'P&L KPO'!C9 | D11: ='P&L 2026 TCO'!D9+'P&L KPO'!D9 | E11: ='P&L 2026 TCO'!E9+'P&L KPO'!E9 | F11: ='P&L 2026 TCO'!F9+'P&L KPO'!F9 | G11: ='P&L 2026 TCO'!G9+'P&L KPO'!G9 | H11: ='P&L 2026 TCO'!H9+'P&L KPO'!H9 | I11: ='P&L 2026 TCO'!I9+'P&L KPO'!I9 | J11: ='P&L 2026 TCO'!J9+'P&L KPO'!J9 | ... N11: ='P&L 2026 TCO'!N9+'P&L KPO'!N9 | O11: =SUM(C11:N11)
B12: Аренда техники | C12: ='P&L 2026 TCO'!C10+'P&L KPO'!C10+'P&L 2026 concrete'!C10 | D12: ='P&L 2026 TCO'!D10+'P&L KPO'!D10+'P&L 2026 concrete'!D10 | E12: ='P&L 2026 TCO'!E10+'P&L KPO'!E10+'P&L 2026 concrete'!E10 | F12: ='P&L 2026 TCO'!F10+'P&L KPO'!F10+'P&L 2026 concrete'!F10 | G12: ='P&L 2026 TCO'!G10+'P&L KPO'!G10+'P&L 2026 concrete'!G10 | H12: ='P&L 2026 TCO'!H10+'P&L KPO'!H10+'P&L 2026 concrete'!H10 | I12: ='P&L 2026 TCO'!I10+'P&L KPO'!I10+'P&L 2026 concrete'!I10 | J12: ='P&L 2026 TCO'!J10+'P&L KPO'!J10+'P&L 2026 concrete'!J10 | ... N12: ='P&L 2026 TCO'!N10+'P&L KPO'!N10+'P&L 2026 concrete'!N10 | O12: =SUM(C12:N12)
B13: База содержание | C13: ='P&L 2026 concrete'!C11 | D13: ='P&L 2026 concrete'!D11 | E13: ='P&L 2026 concrete'!E11 | F13: ='P&L 2026 concrete'!F11 | G13: ='P&L 2026 concrete'!G11 | H13: ='P&L 2026 concrete'!H11 | I13: ='P&L 2026 concrete'!I11 | J13: ='P&L 2026 concrete'!J11 | ... N13: ='P&L 2026 concrete'!N11 | O13: =SUM(C13:N13)
B14: ГСМ | C14: ='P&L 2026 TCO'!C11+'P&L KPO'!C11+'P&L 2026 concrete'!C12 | D14: ='P&L 2026 TCO'!D11+'P&L KPO'!D11+'P&L 2026 concrete'!D12 | E14: ='P&L 2026 TCO'!E11+'P&L KPO'!E11+'P&L 2026 concrete'!E12 | F14: ='P&L 2026 TCO'!F11+'P&L KPO'!F11+'P&L 2026 concrete'!F12 | G14: ='P&L 2026 TCO'!G11+'P&L KPO'!G11+'P&L 2026 concrete'!G12 | H14: ='P&L 2026 TCO'!H11+'P&L KPO'!H11+'P&L 2026 concrete'!H12 | I14: ='P&L 2026 TCO'!I11+'P&L KPO'!I11+'P&L 2026 concrete'!I12 | J14: ='P&L 2026 TCO'!J11+'P&L KPO'!J11+'P&L 2026 concrete'!J12 | ... N14: ='P&L 2026 TCO'!N11+'P&L KPO'!N11+'P&L 2026 concrete'!N12 | O14: =SUM(C14:N14)
B15: Заработная плата | C15: ='P&L 2026 TCO'!C12+'P&L KPO'!C12+'P&L 2026 concrete'!C13 | D15: ='P&L 2026 TCO'!D12+'P&L KPO'!D12+'P&L 2026 concrete'!D13 | E15: ='P&L 2026 TCO'!E12+'P&L KPO'!E12+'P&L 2026 concrete'!E13 | F15: ='P&L 2026 TCO'!F12+'P&L KPO'!F12+'P&L 2026 concrete'!F13 | G15: ='P&L 2026 TCO'!G12+'P&L KPO'!G12+'P&L 2026 concrete'!G13 | H15: ='P&L 2026 TCO'!H12+'P&L KPO'!H12+'P&L 2026 concrete'!H13 | I15: ='P&L 2026 TCO'!I12+'P&L KPO'!I12+'P&L 2026 concrete'!I13 | J15: ='P&L 2026 TCO'!J12+'P&L KPO'!J12+'P&L 2026 concrete'!J13 | ... N15: ='P&L 2026 TCO'!N12+'P&L KPO'!N12+'P&L 2026 concrete'!N13 | O15: =SUM(C15:N15)
B16: Интернет+связь | C16: ='P&L 2026 TCO'!C13+'P&L KPO'!C13+'P&L 2026 concrete'!C14 | D16: ='P&L 2026 TCO'!D13+'P&L KPO'!D13+'P&L 2026 concrete'!D14 | E16: ='P&L 2026 TCO'!E13+'P&L KPO'!E13+'P&L 2026 concrete'!E14 | F16: ='P&L 2026 TCO'!F13+'P&L KPO'!F13+'P&L 2026 concrete'!F14 | G16: ='P&L 2026 TCO'!G13+'P&L KPO'!G13+'P&L 2026 concrete'!G14 | H16: ='P&L 2026 TCO'!H13+'P&L KPO'!H13+'P&L 2026 concrete'!H14 | I16: ='P&L 2026 TCO'!I13+'P&L KPO'!I13+'P&L 2026 concrete'!I14 | J16: ='P&L 2026 TCO'!J13+'P&L KPO'!J13+'P&L 2026 concrete'!J14 | ... N16: ='P&L 2026 TCO'!N13+'P&L KPO'!N13+'P&L 2026 concrete'!N14 | O16: =SUM(C16:N16)
B17: Коммунальные услуги | C17: ='P&L 2026 concrete'!C15 | D17: ='P&L 2026 concrete'!D15 | E17: ='P&L 2026 concrete'!E15 | F17: ='P&L 2026 concrete'!F15 | G17: ='P&L 2026 concrete'!G15 | H17: ='P&L 2026 concrete'!H15 | I17: ='P&L 2026 concrete'!I15 | J17: ='P&L 2026 concrete'!J15 | ... N17: ='P&L 2026 concrete'!N15 | O17: =SUM(C17:N17)
B18: Мед.обслуживание | C18: ='P&L 2026 TCO'!C14+'P&L KPO'!C14 | D18: ='P&L 2026 TCO'!D14+'P&L KPO'!D14 | E18: ='P&L 2026 TCO'!E14+'P&L KPO'!E14 | F18: ='P&L 2026 TCO'!F14+'P&L KPO'!F14 | G18: ='P&L 2026 TCO'!G14+'P&L KPO'!G14 | H18: ='P&L 2026 TCO'!H14+'P&L KPO'!H14 | I18: ='P&L 2026 TCO'!I14+'P&L KPO'!I14 | J18: ='P&L 2026 TCO'!J14+'P&L KPO'!J14 | ... N18: ='P&L 2026 TCO'!N14+'P&L KPO'!N14 | O18: =SUM(C18:N18)
B19: Налоги | C19: ='P&L 2026 TCO'!C15+'P&L KPO'!C15+'P&L 2026 concrete'!C16 | D19: ='P&L 2026 TCO'!D15+'P&L KPO'!D15+'P&L 2026 concrete'!D16 | E19: ='P&L 2026 TCO'!E15+'P&L KPO'!E15+'P&L 2026 concrete'!E16 | F19: ='P&L 2026 TCO'!F15+'P&L KPO'!F15+'P&L 2026 concrete'!F16 | G19: ='P&L 2026 TCO'!G15+'P&L KPO'!G15+'P&L 2026 concrete'!G16 | H19: ='P&L 2026 TCO'!H15+'P&L KPO'!H15+'P&L 2026 concrete'!H16 | I19: ='P&L 2026 TCO'!I15+'P&L KPO'!I15+'P&L 2026 concrete'!I16 | J19: ='P&L 2026 TCO'!J15+'P&L KPO'!J15+'P&L 2026 concrete'!J16 | ... N19: ='P&L 2026 TCO'!N15+'P&L KPO'!N15+'P&L 2026 concrete'!N16 | O19: =SUM(C19:N19)
B20: Прочие услуги | C20: ='P&L 2026 TCO'!C16+'P&L KPO'!C16+'P&L 2026 concrete'!C17 | D20: ='P&L 2026 TCO'!D16+'P&L KPO'!D16+'P&L 2026 concrete'!D17 | E20: ='P&L 2026 TCO'!E16+'P&L KPO'!E16+'P&L 2026 concrete'!E17 | F20: ='P&L 2026 TCO'!F16+'P&L KPO'!F16+'P&L 2026 concrete'!F17 | G20: ='P&L 2026 TCO'!G16+'P&L KPO'!G16+'P&L 2026 concrete'!G17 | H20: ='P&L 2026 TCO'!H16+'P&L KPO'!H16+'P&L 2026 concrete'!H17 | I20: ='P&L 2026 TCO'!I16+'P&L KPO'!I16+'P&L 2026 concrete'!I17 | J20: ='P&L 2026 TCO'!J16+'P&L KPO'!J16+'P&L 2026 concrete'!J17 | ... N20: ='P&L 2026 TCO'!N16+'P&L KPO'!N16+'P&L 2026 concrete'!N17 | O20: =SUM(C20:N20)
B21: Расходны на наем жилья и Суточные | C21: ='P&L 2026 TCO'!C17+'P&L KPO'!C17+'P&L 2026 concrete'!C18 | D21: ='P&L 2026 TCO'!D17+'P&L KPO'!D17+'P&L 2026 concrete'!D18 | E21: ='P&L 2026 TCO'!E17+'P&L KPO'!E17+'P&L 2026 concrete'!E18 | F21: ='P&L 2026 TCO'!F17+'P&L KPO'!F17+'P&L 2026 concrete'!F18 | G21: ='P&L 2026 TCO'!G17+'P&L KPO'!G17+'P&L 2026 concrete'!G18 | H21: ='P&L 2026 TCO'!H17+'P&L KPO'!H17+'P&L 2026 concrete'!H18 | I21: ='P&L 2026 TCO'!I17+'P&L KPO'!I17+'P&L 2026 concrete'!I18 | J21: ='P&L 2026 TCO'!J17+'P&L KPO'!J17+'P&L 2026 concrete'!J18 | ... N21: ='P&L 2026 TCO'!N17+'P&L KPO'!N17+'P&L 2026 concrete'!N18 | O21: =SUM(C21:N21)
B22: Расходы на питание и проживание | C22: ='P&L 2026 TCO'!C18+'P&L KPO'!C18 | D22: ='P&L 2026 TCO'!D18+'P&L KPO'!D17 | E22: ='P&L 2026 TCO'!E18+'P&L KPO'!E18 | F22: ='P&L 2026 TCO'!F18+'P&L KPO'!F18 | G22: ='P&L 2026 TCO'!G18+'P&L KPO'!G18 | H22: ='P&L 2026 TCO'!H18+'P&L KPO'!H18 | I22: ='P&L 2026 TCO'!I18+'P&L KPO'!I18 | J22: ='P&L 2026 TCO'!J18+'P&L KPO'!J18 | K22: ='P&L 2026 TCO'!K18+'P&L KPO'!K18 | L22: ='P&L 2026 TCO'!L18+'P&L KPO'!L18 | ... N22: ='P&L 2026 TCO'!N18+'P&L KPO'!N18 | O22: =SUM(C22:N22)
B23: Расходы на проезд | C23: ='P&L 2026 TCO'!C19+'P&L KPO'!C19+'P&L 2026 concrete'!C19 | D23: ='P&L 2026 TCO'!D19+'P&L KPO'!D19+'P&L 2026 concrete'!D19 | E23: ='P&L 2026 TCO'!E19+'P&L KPO'!E19+'P&L 2026 concrete'!E19 | F23: ='P&L 2026 TCO'!F19+'P&L KPO'!F19+'P&L 2026 concrete'!F19 | G23: ='P&L 2026 TCO'!G19+'P&L KPO'!G19+'P&L 2026 concrete'!G19 | H23: ='P&L 2026 TCO'!H19+'P&L KPO'!H19+'P&L 2026 concrete'!H19 | I23: ='P&L 2026 TCO'!I19+'P&L KPO'!I19+'P&L 2026 concrete'!I19 | J23: ='P&L 2026 TCO'!J19+'P&L KPO'!J19+'P&L 2026 concrete'!J19 | ... N23: ='P&L 2026 TCO'!N19+'P&L KPO'!N19+'P&L 2026 concrete'!N19 | O23: =SUM(C23:N23)
B24: Расходы по доставке | C24: ='P&L 2026 TCO'!C20+'P&L KPO'!C20 | D24: ='P&L 2026 TCO'!D20+'P&L KPO'!D20 | E24: ='P&L 2026 TCO'!E20+'P&L KPO'!E20 | F24: ='P&L 2026 TCO'!F20+'P&L KPO'!F20 | G24: ='P&L 2026 TCO'!G20+'P&L KPO'!G20 | H24: ='P&L 2026 TCO'!H20+'P&L KPO'!H20 | I24: ='P&L 2026 TCO'!I20+'P&L KPO'!I20 | J24: ='P&L 2026 TCO'!J20+'P&L KPO'!J20 | ... N24: ='P&L 2026 TCO'!N20+'P&L KPO'!N20 | O24: =SUM(C24:N24)
B25: Расходы по обучению | C25: ='P&L 2026 TCO'!C21+'P&L KPO'!C21 | D25: ='P&L 2026 TCO'!D21+'P&L KPO'!D21 | E25: ='P&L 2026 TCO'!E21+'P&L KPO'!E21 | F25: ='P&L 2026 TCO'!F21+'P&L KPO'!F21 | G25: ='P&L 2026 TCO'!G21+'P&L KPO'!G21 | H25: ='P&L 2026 TCO'!H21+'P&L KPO'!H21 | I25: ='P&L 2026 TCO'!I21+'P&L KPO'!I21 | J25: ='P&L 2026 TCO'!J21+'P&L KPO'!J21 | ... N25: ='P&L 2026 TCO'!N21+'P&L KPO'!N21 | O25: =SUM(C25:N25)
B26: Расходы по перевозке | C26: ='P&L 2026 TCO'!C22+'P&L KPO'!C22+'P&L 2026 concrete'!C20 | D26: ='P&L 2026 TCO'!D22+'P&L KPO'!D22+'P&L 2026 concrete'!D20 | E26: ='P&L 2026 TCO'!E22+'P&L KPO'!E22+'P&L 2026 concrete'!E20 | F26: ='P&L 2026 TCO'!F22+'P&L KPO'!F22+'P&L 2026 concrete'!F20 | G26: ='P&L 2026 TCO'!G22+'P&L KPO'!G22+'P&L 2026 concrete'!G20 | H26: ='P&L 2026 TCO'!H22+'P&L KPO'!H22+'P&L 2026 concrete'!H20 | I26: ='P&L 2026 TCO'!I22+'P&L KPO'!I22+'P&L 2026 concrete'!I20 | J26: ='P&L 2026 TCO'!J22+'P&L KPO'!J22+'P&L 2026 concrete'!J20 | ... N26: ='P&L 2026 TCO'!N22+'P&L KPO'!N22+'P&L 2026 concrete'!N20 | O26: =SUM(C26:N26)
B27: Расходы по СИЗ | C27: ='P&L 2026 TCO'!C23+'P&L KPO'!C23+'P&L 2026 concrete'!C21 | D27: ='P&L 2026 TCO'!D23+'P&L KPO'!D23+'P&L 2026 concrete'!D21 | E27: ='P&L 2026 TCO'!E23+'P&L KPO'!E23+'P&L 2026 concrete'!E21 | F27: ='P&L 2026 TCO'!F23+'P&L KPO'!F23+'P&L 2026 concrete'!F21 | G27: ='P&L 2026 TCO'!G23+'P&L KPO'!G23+'P&L 2026 concrete'!G21 | H27: ='P&L 2026 TCO'!H23+'P&L KPO'!H23+'P&L 2026 concrete'!H21 | I27: ='P&L 2026 TCO'!I23+'P&L KPO'!I23+'P&L 2026 concrete'!I21 | J27: ='P&L 2026 TCO'!J23+'P&L KPO'!J23+'P&L 2026 concrete'!J21 | ... N27: ='P&L 2026 TCO'!N23+'P&L KPO'!N23+'P&L 2026 concrete'!N21 | O27: =SUM(C27:N27)
B28: Расходы на утилизацию+ экологию | C28: ='P&L 2026 TCO'!C24+'P&L KPO'!C24+'P&L 2026 concrete'!C22 | D28: ='P&L 2026 TCO'!D24+'P&L KPO'!D24+'P&L 2026 concrete'!D22 | E28: ='P&L 2026 TCO'!E24+'P&L KPO'!E24+'P&L 2026 concrete'!E22 | F28: ='P&L 2026 TCO'!F24+'P&L KPO'!F24+'P&L 2026 concrete'!F22 | G28: ='P&L 2026 TCO'!G24+'P&L KPO'!G24+'P&L 2026 concrete'!G22 | H28: ='P&L 2026 TCO'!H24+'P&L KPO'!H24+'P&L 2026 concrete'!H22 | I28: ='P&L 2026 TCO'!I24+'P&L KPO'!I24+'P&L 2026 concrete'!I22 | J28: ='P&L 2026 TCO'!J24+'P&L KPO'!J24+'P&L 2026 concrete'!J22 | ... N28: ='P&L 2026 TCO'!N24+'P&L KPO'!N24+'P&L 2026 concrete'!N22 | O28: =SUM(C28:N28)
B29: Расходы на ремонт авто/ оборудования | C29: ='P&L 2026 TCO'!C25+'P&L KPO'!C25+'P&L 2026 concrete'!C23 | D29: ='P&L 2026 TCO'!D25+'P&L KPO'!D25+'P&L 2026 concrete'!D23 | E29: ='P&L 2026 TCO'!E25+'P&L KPO'!E25+'P&L 2026 concrete'!E23 | F29: ='P&L 2026 TCO'!F25+'P&L KPO'!F25+'P&L 2026 concrete'!F23 | G29: ='P&L 2026 TCO'!G25+'P&L KPO'!G25+'P&L 2026 concrete'!G23 | H29: ='P&L 2026 TCO'!H25+'P&L KPO'!H25+'P&L 2026 concrete'!H23 | I29: ='P&L 2026 TCO'!I25+'P&L KPO'!I25+'P&L 2026 concrete'!I23 | J29: ='P&L 2026 TCO'!J25+'P&L KPO'!J25+'P&L 2026 concrete'!J23 | ... N29: ='P&L 2026 TCO'!N25+'P&L KPO'!N25+'P&L 2026 concrete'!N23 | O29: =SUM(C29:N29)
B30: Себестоимость реализованной продукции и оказанных услуг/ подрядчики | C30: ='P&L 2026 TCO'!C26+'P&L KPO'!C26+'P&L 2026 concrete'!C24 | D30: ='P&L 2026 TCO'!D26+'P&L KPO'!D26+'P&L 2026 concrete'!D24 | E30: ='P&L 2026 TCO'!E26+'P&L KPO'!E26+'P&L 2026 concrete'!E24 | F30: ='P&L 2026 TCO'!F26+'P&L KPO'!F26+'P&L 2026 concrete'!F24 | G30: ='P&L 2026 TCO'!G26+'P&L KPO'!G26+'P&L 2026 concrete'!G24 | H30: ='P&L 2026 TCO'!H26+'P&L KPO'!H26+'P&L 2026 concrete'!H24 | I30: ='P&L 2026 TCO'!I26+'P&L KPO'!I26+'P&L 2026 concrete'!I24 | J30: ='P&L 2026 TCO'!J26+'P&L KPO'!J26+'P&L 2026 concrete'!J24 | ... N30: ='P&L 2026 TCO'!N26+'P&L KPO'!N26+'P&L 2026 concrete'!N24 | O30: =SUM(C30:N30)
B31: Содержание на сайте офиса, контейнера, базы, ком.усл | C31: ='P&L 2026 TCO'!C27+'P&L KPO'!C27 | D31: ='P&L 2026 TCO'!D27+'P&L KPO'!D27 | E31: ='P&L 2026 TCO'!E27+'P&L KPO'!E27 | F31: ='P&L 2026 TCO'!F27+'P&L KPO'!F27 | G31: ='P&L 2026 TCO'!G27+'P&L KPO'!G27 | H31: ='P&L 2026 TCO'!H27+'P&L KPO'!H27 | I31: ='P&L 2026 TCO'!I27+'P&L KPO'!I27 | J31: ='P&L 2026 TCO'!J27+'P&L KPO'!J27 | ... N31: ='P&L 2026 TCO'!N27+'P&L KPO'!N27 | O31: =SUM(C31:N31)
B32: Списанные материалы | C32: ='P&L 2026 TCO'!C28+'P&L KPO'!C28+'P&L 2026 concrete'!C25 | D32: ='P&L 2026 TCO'!D28+'P&L KPO'!D28+'P&L 2026 concrete'!D25 | E32: ='P&L 2026 TCO'!E28+'P&L KPO'!E28+'P&L 2026 concrete'!E25 | F32: ='P&L 2026 TCO'!F28+'P&L KPO'!F28+'P&L 2026 concrete'!F25 | G32: ='P&L 2026 TCO'!G28+'P&L KPO'!G28+'P&L 2026 concrete'!G25 | H32: ='P&L 2026 TCO'!H28+'P&L KPO'!H28+'P&L 2026 concrete'!H25 | I32: ='P&L 2026 TCO'!I28+'P&L KPO'!I28+'P&L 2026 concrete'!I25 | J32: ='P&L 2026 TCO'!J28+'P&L KPO'!J28+'P&L 2026 concrete'!J25 | ... N32: ='P&L 2026 TCO'!N28+'P&L KPO'!N28+'P&L 2026 concrete'!N25 | O32: =SUM(C32:N32)
B33: Страхование | C33: ='P&L 2026 TCO'!C29+'P&L KPO'!C29+'P&L 2026 concrete'!C26 | D33: ='P&L 2026 TCO'!D29+'P&L KPO'!D29+'P&L 2026 concrete'!D26 | E33: ='P&L 2026 TCO'!E29+'P&L KPO'!E29+'P&L 2026 concrete'!E26 | F33: ='P&L 2026 TCO'!F29+'P&L KPO'!F29+'P&L 2026 concrete'!F26 | G33: ='P&L 2026 TCO'!G29+'P&L KPO'!G29+'P&L 2026 concrete'!G26 | H33: ='P&L 2026 TCO'!H29+'P&L KPO'!H29+'P&L 2026 concrete'!H26 | I33: ='P&L 2026 TCO'!I29+'P&L KPO'!I29+'P&L 2026 concrete'!I26 | J33: ='P&L 2026 TCO'!J29+'P&L KPO'!J29+'P&L 2026 concrete'!J26 | ... N33: ='P&L 2026 TCO'!N29+'P&L KPO'!N29+'P&L 2026 concrete'!N26 | O33: =SUM(C33:N33)
B34: Расходы на финансирование | C34: ='P&L 2026 TCO'!C30+'P&L KPO'!C30+'P&L 2026 concrete'!C27 | D34: ='P&L 2026 TCO'!D30+'P&L KPO'!D30+'P&L 2026 concrete'!D27 | E34: ='P&L 2026 TCO'!E30+'P&L KPO'!E30+'P&L 2026 concrete'!E27 | F34: ='P&L 2026 TCO'!F30+'P&L KPO'!F30+'P&L 2026 concrete'!F27 | G34: ='P&L 2026 TCO'!G30+'P&L KPO'!G30+'P&L 2026 concrete'!G27 | H34: ='P&L 2026 TCO'!H30+'P&L KPO'!H30+'P&L 2026 concrete'!H27 | I34: ='P&L 2026 TCO'!I30+'P&L KPO'!I30+'P&L 2026 concrete'!I27 | J34: ='P&L 2026 TCO'!J30+'P&L KPO'!J30+'P&L 2026 concrete'!J27 | ... N34: ='P&L 2026 TCO'!N30+'P&L KPO'!N30+'P&L 2026 concrete'!N27
B35: Итого | C35: =SUM(C9:C34) | D35: =SUM(D9:D34) | E35: =SUM(E9:E34) | F35: =SUM(F9:F34) | G35: =SUM(G9:G34) | H35: =SUM(H9:H34) | I35: =SUM(I9:I34) | J35: =SUM(J9:J34) | ... N35: =SUM(N9:N34) | O35: =SUM(O9:O33)
B36: Административные расходы
B37: Расходы по заработной плате | O37: =SUM(C36:N36)
B38: Налоги | O38: =SUM(C37:N37)
B39: ГСМ | O39: =SUM(C38:N38)
B40: Банковская комиссия | O40: =SUM(C39:N39)
B41: Амортизация ФА | O41: =SUM(C40:N40)
B42: Подписка | O42: =SUM(C41:N41)
B43: Аудиторские/ консультационные услуги | O43: =SUM(C42:N42)
B44: Услуги связи+интернет | O44: =SUM(C43:N43)
B45: Мед осмотр | O45: =SUM(C44:N44)
B46: Расходы по страховке | O46: =SUM(C45:N45)
B47: Командировочные расходы(проезд+проживание+суточные) | O47: =SUM(C46:N46)
B48: Содержание офиса | O48: =SUM(C47:N47)
B49: Обучение сотрудников | O49: =SUM(C48:N48)
B50: Прочие расходы | C50: ='P&L 2026 TCO'!C33+'P&L KPO'!C33+'P&L 2026 concrete'!C49 | D50: ='P&L 2026 TCO'!D33+'P&L KPO'!D33+'P&L 2026 concrete'!D49 | E50: ='P&L 2026 TCO'!E33+'P&L KPO'!E33+'P&L 2026 concrete'!E49 | F50: ='P&L 2026 TCO'!F33+'P&L KPO'!F33+'P&L 2026 concrete'!F49 | G50: ='P&L 2026 TCO'!G33+'P&L KPO'!G33+'P&L 2026 concrete'!G49 | H50: ='P&L 2026 TCO'!H33+'P&L KPO'!H33+'P&L 2026 concrete'!H49 | I50: ='P&L 2026 TCO'!I33+'P&L KPO'!I33+'P&L 2026 concrete'!I49 | J50: ='P&L 2026 TCO'!J33+'P&L KPO'!J33+'P&L 2026 concrete'!J49 | ... N50: ='P&L 2026 TCO'!N33+'P&L KPO'!N33+'P&L 2026 concrete'!N49 | O50: =SUM(C49:N49)
B51: Услуги по доставке | O51: =SUM(C50:N50)
B52: Вознаграждения по лизингу | O52: =SUM(C51:N51)
B53: Итого | C53: =SUM(C37:C52) | D53: =SUM(D37:D52) | E53: =SUM(E37:E52) | F53: =SUM(F37:F52) | G53: =SUM(G37:G52) | H53: =SUM(H37:H52) | I53: =SUM(I37:I52) | J53: =SUM(J37:J52) | ... N53: =SUM(N37:N52) | O53: =SUM(O36:O51)
B54: Прочие доходы | O54: =SUM(C53:N53)
B55: Прочие расходы | C55: ='P&L 2026 TCO'!C33+'P&L KPO'!C33+'P&L 2026 concrete'!C48 | D55: ='P&L 2026 TCO'!D33+'P&L KPO'!D33+'P&L 2026 concrete'!D48 | E55: ='P&L 2026 TCO'!E33+'P&L KPO'!E33+'P&L 2026 concrete'!E48 | F55: ='P&L 2026 TCO'!F33+'P&L KPO'!F33+'P&L 2026 concrete'!F48 | G55: ='P&L 2026 TCO'!G33+'P&L KPO'!G33+'P&L 2026 concrete'!G48 | H55: ='P&L 2026 TCO'!H33+'P&L KPO'!H33+'P&L 2026 concrete'!H48 | I55: ='P&L 2026 TCO'!I33+'P&L KPO'!I33+'P&L 2026 concrete'!I48 | J55: ='P&L 2026 TCO'!J33+'P&L KPO'!J33+'P&L 2026 concrete'!J48 | ... N55: ='P&L 2026 TCO'!N33+'P&L KPO'!N33+'P&L 2026 concrete'!N48 | O55: =SUM(C54:N54)
B56: ДОХОД ДО КПН | C56: =C7-C35-C53+C54-C55 | D56: =D7-D35-D53+D54-D55 | E56: =E7-E35-E53+E54-E55 | F56: =F7-F35-F53+F54-F55 | G56: =G7-G35-G53+G54-G55 | H56: =H7-H35-H53+H54-H55 | I56: =I7-I35-I53+I54-I55 | J56: =J7-J35-J53+J54-J55 | ... N56: =N7-N35-N53+N54-N55 | O56: =O7-O34-O52+O53-O54
B57: КПН | C57: =C56*0.2 | D57: =D56*0.2 | E57: =E56*0.2 | F57: =F56*0.2 | G57: =G56*0.2 | H57: =H56*0.2 | I57: =I56*0.2 | J57: =J56*0.2 | ... N57: =N56*0.2 | O57: =SUM(C56:N56)
B58: ЧИСТЫЙ ДОХОД | C58: =C56-C57 | D58: =D56-D57 | E58: =E56-E57 | F58: =F56-F57 | G58: =G56-G57 | H58: =H56-H57 | I58: =I56-I57 | J58: =J56-J57 | ... N58: =N56-N57 | O58: =O55-O56
B60: КОНТРОЛЬ СВЕРКИ С ОСВ | N60: Рентабельность до КПН | O60: =O55/O7
B61: ОСВ 1С (сч. 5610)
B62: КПН (сч. 7710)
B63: ОСВ результат до КПН | C63: =C61+C62 | D63: =D61+D62 | E63: =E61+E62 | F63: =F61+F62 | G63: =G61+G62 | H63: =H61+H62 | I63: =I61+I62 | J63: =J61+J62 | ... N63: =N61+N62
B64: P&L доход до КПН | C64: =C56 | D64: =D56 | E64: =E56 | F64: =F56 | G64: =G56 | H64: =H56 | I64: =I56 | J64: =J56 | ... N64: =N56
B65: Разница (контроль) | C65: =C63-C64 | D65: =D63-D64 | E65: =E63-E64 | F65: =F63-F64 | G65: =G63-G64 | H65: =H63-H64 | I65: =I63-I64 | J65: =J63-J64 | ... N65: =N63-N64

Sheet P&L 2026 TCO
B1: Доход от реализации | C1: Январь | D1: Февраль | E1: Март | F1: Апрель | G1: Май | H1: Июнь | I1: Июль | J1: Август | K1: Сентябрь | L1: Октябрь | M1: Ноябрь | N1: Декабрь | O1: ИТОГО
B3: Доход от реализации | O3: =SUM(C3:N3)
O4: =SUM(I4:N4)
B5: ИТОГО | C5: =C3 | D5: =D3 | E5: =E3 | F5: =F3 | G5: =G3 | H5: =H3 | I5: =I3 | J5: =J3 | ... N5: =N3 | O5: =SUM(O2:O4)
B6: Расходы ТШО
B7: GPS | O7: =SUM(C7:N7)
B8: Амортизация | O8: =SUM(C8:N8)
B9: Аренда офиса | O9: =SUM(C9:N9)
B10: Аренда техники | O10: =SUM(C10:N10)
B11: ГСМ | O11: =SUM(C11:N11)
B12: Заработная плата | O12: =SUM(C12:N12)
B13: Интернет+ связь | O13: =SUM(C13:N13)
B14: Мед.обслуживание | O14: =SUM(C14:N14)
B15: Налоги | O15: =SUM(C15:N15)
B16: Прочие услуги сторонних организаций | O16: =SUM(C16:N16)
B17: Расходны на наем жилья и Суточные | O17: =SUM(C17:N17)
B18: Расходы на питание и проживание | O18: =SUM(C18:N18)
... B29: Страхование | O29: =SUM(C29:N29)
B30: Расходы на финансирование
B31: Итого | C31: =SUM(C7:C30) | D31: =SUM(D7:D30) | E31: =SUM(E7:E30) | F31: =SUM(F7:F30) | G31: =SUM(G7:G30) | H31: =SUM(H7:H30) | I31: =SUM(I7:I30) | J31: =SUM(J7:J30) | ... N31: =SUM(N7:N30) | O31: =SUM(O16:O29)
B32: Прочие доходы | O32: =SUM(C31:N31)
B33: Прочие расходы | O33: =SUM(C32:N32)
B34: ДОХОД ДО КПН | C34: =C5-C31+C32-C33 | D34: =D5-D31+D32-D33 | E34: =E5-E31+E32-E33 | F34: =F5-F31+F32-F33 | G34: =G5-G31+G32-G33 | H34: =H5-H31+H32-H33 | I34: =I5-I31+I32-I33 | J34: =J5-J31+J32-J33 | ... N34: =N5-N31+N32-N33 | O34: =O5-O30+O31-O32
B35: КПН | C35: =C34*0.2 | D35: =D34*0.2 | E35: =E34*0.2 | F35: =F34*0.2 | G35: =G34*0.2 | H35: =H34*0.2 | I35: =I34*0.2 | J35: =J34*0.2 | ... N35: =N34*0.2 | O35: =SUM(C34:N34)
B36: ЧИСТЫЙ ДОХОД | C36: =C34-C35 | D36: =D34-D35 | E36: =E34-E35 | F36: =F34-F35 | G36: =G34-G35 | H36: =H34-H35 | I36: =I34-I35 | J36: =J34-J35 | ... N36: =N34-N35 | O36: =O33-O34
N38: Рентабельность до КПН | O38: =O33/O5

Sheet P&L KPO
B1: Доход от реализации | C1: Январь | D1: Февраль | E1: Март | F1: Апрель | G1: Май | H1: Июнь | I1: Июль | J1: Август | K1: Сентябрь | L1: Октябрь | M1: Ноябрь | N1: Декабрь | O1: ИТОГО
B3: Доход от реализации | O3: =SUM(C3:N3)
O4: =SUM(I4:N4)
B5: ИТОГО | C5: =C3 | D5: =D3 | E5: =E3 | F5: =F3 | G5: =G3 | H5: =H3 | I5: =I3 | J5: =J3 | ... N5: =N3 | O5: =SUM(O2:O4)
B6: Расходы ТШО
B7: GPS | O7: =SUM(C7:N7)
B8: Амортизация | O8: =SUM(C8:N8)
B9: Аренда офиса | O9: =SUM(C9:N9)
B10: Аренда техники | O10: =SUM(C10:N10)
B11: ГСМ | O11: =SUM(C11:N11)
B12: Заработная плата | O12: =SUM(C12:N12)
B13: Интернет+связь | O13: =SUM(C13:N13)
B14: Мед.обслуживание | O14: =SUM(C14:N14)
B15: Налоги | O15: =SUM(C15:N15)
B16: Прочие услуги
B17: Расходны на наем жилья и Суточные | O17: =SUM(C17:N17)
B18: Расходы на питание и проживание | O18: =SUM(C18:N18)
B19: Расходы на проезд | O19: =SUM(C19:N19)
B20: Расходы по доставке | O20: =SUM(C20:N20)
B21: Расходы по обучению | O21: =SUM(C21:N21)
B22: Расходы по перевозке | O22: =SUM(C22:N22)
B23: Расходы по СИЗ | O23: =SUM(C23:N23)
B24: Расходы на утилизацию | O24: =SUM(C24:N24)
B25: Расходы на ремонт авто/ оборудования | O25: =SUM(C25:N25)
B26: Услуги сторонних/ подрядных организаций | O26: =SUM(C26:N26)
B27: Содержание на сайте офиса+ контейнера | O27: =SUM(C27:N27)
B28: Списанные материалы | O28: =SUM(C28:N28)
B29: Страхование | O29: =SUM(C29:N29)
B30: Расходы на финансирование
B31: Итого | C31: =SUM(C7:C30) | D31: =SUM(D7:D30) | E31: =SUM(E7:E30) | F31: =SUM(F7:F30) | G31: =SUM(G7:G30) | H31: =SUM(H7:H30) | I31: =SUM(I7:I30) | J31: =SUM(J7:J30) | ... N31: =SUM(N7:N30) | O31: =SUM(O14:O29)
B32: Прочие доходы | O32: =SUM(C31:N31)
B33: Прочие расходы | O33: =SUM(C32:N32)
B34: ДОХОД ДО КПН | C34: =C5-C31+C32-C33 | D34: =D5-D31+D32-D33 | E34: =E5-E31+E32-E33 | F34: =F5-F31+F32-F33 | G34: =G5-G31+G32-G33 | H34: =H5-H31+H32-H33 | I34: =I5-I31+I32-I33 | J34: =J5-J31+J32-J33 | ... N34: =N5-N31+N32-N33 | O34: =O5-O30+O31-O32
B35: КПН | C35: =C34*0.2 | D35: =D34*0.2 | E35: =E34*0.2 | F35: =F34*0.2 | G35: =G34*0.2 | H35: =H34*0.2 | I35: =I34*0.2 | J35: =J34*0.2 | ... N35: =N34*0.2 | O35: =SUM(C34:N34)
B36: ЧИСТЫЙ ДОХОД | C36: =C34-C35 | D36: =D34-D35 | E36: =E34-E35 | F36: =F34-F35 | G36: =G34-G35 | H36: =H34-H35 | I36: =I34-I35 | J36: =J34-J35 | ... N36: =N34-N35 | O36: =O33-O34
N38: Рентабельность до КПН | O38: =O33/O5

Sheet P&L 2026 concrete
B1: Доход от реализации | C1: Январь | D1: Февраль | E1: Март | F1: Апрель | G1: Май | H1: Июнь | I1: Июль | J1: Август | K1: Сентябрь | L1: Октябрь | M1: Ноябрь | N1: Декабрь | O1: ИТОГО
B3: Доход от реализации бетона | O3: =SUM(C3:N3)
B4: Доход от сдачи в аренду | O4: =SUM(C4:N4)
B5: Прочий доход | O5: =SUM(C5:N5)
B6: Прочие доходы (субсидии Даму) | O6: =SUM(C6:N6)
B7: ИТОГО | C7: =SUM(C2:C6) | D7: =SUM(D2:D6) | E7: =SUM(E2:E6) | F7: =SUM(F2:F6) | G7: =SUM(G2:G6) | H7: =SUM(H2:H6) | I7: =SUM(I2:I6) | J7: =SUM(J2:J6) | ... O7: =SUM(O2:O6)
B8: Прямые расходы Бетон
B9: GPS | O9: =SUM(C9:N9)
B10: Аренда техники | O10: =SUM(C10:N10)
B11: База содержание | O11: =SUM(C11:N11)
B12: ГСМ | O12: =SUM(C12:N12)
B13: Заработная плата | O13: =SUM(C13:N13)
B14: Интернет+связь | O14: =SUM(C14:N14)
B15: Коммунальные услуги | O15: =SUM(C15:N15)
B16: Налоги | O16: =SUM(C16:N16)
B17: Прочие расходы | O17: =SUM(C17:N17)
B18: Расходны на наем жилья (Эркан) и Суточные | O18: =SUM(C18:N18)
B19: Расходы на проезд | O19: =SUM(C19:N19)
B20: Расходы по перевозке | O20: =SUM(C20:N20)
... B26: Страхование | O26: =SUM(C26:N26)
B27: Расходы на финансирование
B28: Амортизация
B29: Итого | C29: =SUM(C9:C28) | D29: =SUM(D9:D28) | E29: =SUM(E9:E28) | F29: =SUM(F9:F28) | G29: =SUM(G9:G28) | H29: =SUM(H9:H28) | I29: =SUM(I9:I28) | J29: =SUM(J9:J28) | ... N29: =SUM(N9:N28) | O29: =SUM(O19:O26)
B30: Административные расходы
B31: Расходы по заработной плате | O31: =SUM(C29:N29)
B32: Налоги | O32: =SUM(C30:N30)
B33: ГСМ | O33: =SUM(C31:N31)
B34: Банковская комиссия | O34: =SUM(C32:N32)
B35: Амортизация ФА | O35: =SUM(C33:N33)
B36: Подписка | O36: =SUM(C34:N34)
B37: Аудиторские/ консультационные услуги | O37: =SUM(C35:N35)
B38: Услуги связи+интернет | O38: =SUM(C36:N36)
B39: Мед осмотр | O39: =SUM(C37:N37)
B40: Расходы по страховке | O40: =SUM(C38:N38)
B41: Командировочные расходы(проезд+проживание+суточные) | O41: =SUM(C39:N39)
B42: Содержание офиса | O42: =SUM(C40:N40)
... B46: Вознаграждения по лизингу | O46: =SUM(C44:N44)
B47: Итого | C47: =SUM(C31:C46) | D47: =SUM(D31:D46) | E47: =SUM(E31:E46) | F47: =SUM(F31:F46) | G47: =SUM(G31:G46) | H47: =SUM(H31:H46) | I47: =SUM(I31:I46) | J47: =SUM(J31:J46) | ... N47: =SUM(N31:N46) | O47: =SUM(O29:O44)
B48: Прочие доходы | O48: =SUM(C46:N46)
B49: Прочие расходы | O49: =SUM(C47:N47)
B50: ДОХОД ДО КПН | C50: =C7-C29-C47+C48-C49 | D50: =D7-D29-D47+D48-D49 | E50: =E7-E29-E47+E48-E49 | F50: =F7-F29-F47+F48-F49 | G50: =G7-G29-G47+G48-G49 | H50: =H7-H29-H47+H48-H49 | I50: =I7-I29-I47+I48-I49 | J50: =J7-J29-J47+J48-J49 | ... N50: =N7-N29-N47+N48-N49 | O50: =O7-O27-O45+O46-O47
B51: КПН | C51: =C50*0.2 | D51: =D50*0.2 | E51: =E50*0.2 | F51: =F50*0.2 | G51: =G50*0.2 | H51: =H50*0.2 | I51: =I50*0.2 | J51: =J50*0.2 | ... N51: =N50*0.2 | O51: =SUM(C49:N49)
B52: ЧИСТЫЙ ДОХОД | C52: =C50-C51 | D52: =D50-D51 | E52: =E50-E51 | F52: =F50-F51 | G52: =G50-G51 | H52: =H50-H51 | I52: =I50-I51 | J52: =J50-J51 | ... N52: =N50-N51 | O52: =O48-O49
C54: =1-C29/C7 | D54: =1-D29/D7 | E54: =1-E29/E7 | F54: =1-F29/F7 | G54: =1-G29/G7 | H54: =1-H29/H7 | I54: =1-I29/I7 | J54: =1-J29/J7 | ... N54: =1-N29/N7
N56: Рентабельность до КПН | O56: =O48/O7
